strenc/__init__.py
strenccli/__init__.py
strenccli/_main.py
strenc-0.3.2.dist-info/LICENCE
strenc-0.3.2.dist-info/METADATA
strenc-0.3.2.dist-info/WHEEL
strenc-0.3.2.dist-info/entry_points.txt
strenc-0.3.2.dist-info/top_level.txt
strenc-0.3.2.dist-info/RECORD
