Metadata-Version: 2.1
Name: strenc
Version: 0.3.2
Summary: A simple fully customizable string encoder and decoder
Home-page: https://github.com/sdcard2008/strenc
Author: Saptak De
Author-email: saptak1234hehe@gmail.com
License-File: LICENCE
Requires-Dist: setuptools (==65.6.3)
